{"version": "1", "message": "ERROR: Hidden Testcases server unreachable.", "problem_id": "cspp2_m10_a1_1", "user_id": "Mounika2010", "score": {"sample": {"0": {"execution_time": 0.28618860244750977, "passed": true}, "1": {"execution_time": 0.19586777687072754, "passed": true}, "2": {"execution_time": 0.22863316535949707, "passed": true}, "3": {"execution_time": 0.2284541130065918, "passed": true}, "4": {"execution_time": 0.2387557029724121, "passed": false}, "5": {"execution_time": 0.2537989616394043, "passed": false}, "6": {"execution_time": 0.19485116004943848, "passed": false}, "7": {"execution_time": 0.26911067962646484, "passed": false}}}, "check_style_score": "0/1"}